{
  "url" : "https://github.com/nosqlbench/nosqlbench/pull/873",
  "project" : "nosqlbench",
  "projectOrganisation" : "nosqlbench",
  "breakingCommit" : "77f31d1939d479ba69b36b11b08f029511827f1c",
  "prAuthor" : "human",
  "preCommitAuthor" : "human",
  "breakingCommitAuthor" : "human",
  "updatedDependency" : {
    "dependencyGroupID" : "io.swagger.core.v3",
    "dependencyArtifactID" : "swagger-models",
    "previousVersion" : "2.2.6",
    "newVersion" : "2.2.7",
    "dependencyScope" : "compile",
    "versionUpdateType" : "patch",
    "dependencySection" : "dependencies"
  },
  "javaVersionUsedForReproduction" : "11"
}